{
  "days": [
    {
      "id": "1",
      "day": 1
    },
    {
      "id": "2",
      "day": 2
    },
    {
      "id": "3",
      "day": 3
    },
    {
      "id": "4",
      "day": 4
    },
    {
      "id": "3493",
      "day": 5
    },
    {
      "id": "7841",
      "day": 6
    },
    {
      "id": "267b",
      "day": 7
    },
    {
      "id": "0abb",
      "day": 8
    },
    {
      "id": "b5fd",
      "day": 9
    },
    {
      "id": "96d3",
      "day": 10
    },
    {
      "id": "8f6e",
      "day": 11
    },
    {
      "id": "cf3e",
      "day": 12
    },
    {
      "id": "b587",
      "day": 13
    },
    {
      "id": "a290",
      "day": 14
    }
  ],
  "words": [
    {
      "id": "1",
      "day": 1,
      "eng": "apple",
      "kor": "사과",
      "isDone": false
    },
    {
      "id": "3",
      "day": 1,
      "eng": "setting",
      "kor": "설정",
      "isDone": false
    },
    {
      "id": "4",
      "day": 1,
      "eng": "prefernece",
      "kor": "설정",
      "isDone": false
    },
    {
      "id": "5",
      "day": 1,
      "eng": "initialize",
      "kor": "초기화",
      "isDone": false
    },
    {
      "id": "6",
      "day": 1,
      "eng": "exclude",
      "kor": "배제하다",
      "isDone": false
    },
    {
      "id": "7",
      "day": 1,
      "eng": "caption",
      "kor": "페이지제목",
      "isDone": false
    },
    {
      "id": "8",
      "day": 2,
      "eng": "issue",
      "kor": "문제",
      "isDone": true
    },
    {
      "id": "9",
      "day": 2,
      "eng": "individual",
      "kor": "개인",
      "isDone": true
    },
    {
      "id": "10",
      "day": 2,
      "eng": "syntax",
      "kor": "구문",
      "isDone": false
    },
    {
      "id": "11",
      "day": 2,
      "eng": "satatement",
      "kor": "문장",
      "isDone": false
    },
    {
      "id": "12",
      "day": 2,
      "eng": "expression",
      "kor": "평가식",
      "isDone": false
    },
    {
      "id": "13",
      "day": 3,
      "eng": "operator",
      "kor": "연산자",
      "isDone": true
    },
    {
      "id": "14",
      "day": 2,
      "eng": "signature",
      "kor": "리턴타입",
      "isDone": false
    },
    {
      "id": "15",
      "day": 3,
      "eng": "inheritance",
      "kor": "상속",
      "isDone": false
    },
    {
      "id": "16",
      "day": 3,
      "eng": "stack",
      "kor": "쌓다",
      "isDone": false
    },
    {
      "id": "17",
      "day": 3,
      "eng": "token",
      "kor": "표시, 증거",
      "isDone": false
    },
    {
      "id": "9107",
      "eng": "3",
      "kor": "3",
      "day": "1",
      "isDone": false
    },
    {
      "id": "19c5",
      "eng": "dog",
      "kor": "강아지",
      "day": "1",
      "isDone": true
    },
    {
      "id": "2675",
      "eng": "cat",
      "kor": "고양이",
      "day": "1",
      "isDone": false
    },
    {
      "id": "3487",
      "eng": "banana",
      "kor": "바나나",
      "day": "2",
      "isDone": false
    },
    {
      "id": "e099",
      "eng": "영어",
      "kor": "한글",
      "day": "2",
      "isDone": false
    },
    {
      "id": "b13a",
      "eng": "2",
      "kor": "2",
      "day": "1",
      "isDone": false
    },
    {
      "id": "4bb7",
      "eng": "2",
      "kor": "2",
      "day": "1",
      "isDone": false
    },
    {
      "id": "25b1",
      "eng": "ㄴ",
      "kor": "ㄴ",
      "day": "1",
      "isDone": false
    },
    {
      "id": "a133",
      "eng": "22",
      "kor": "22",
      "day": "1",
      "isDone": false
    },
    {
      "id": "e0cf",
      "eng": "123",
      "kor": "123",
      "day": "2",
      "isDone": false
    },
    {
      "id": "0ae8",
      "eng": "234",
      "kor": "234",
      "day": "1",
      "isDone": false
    },
    {
      "id": "61d8",
      "eng": "11",
      "kor": "11",
      "day": "1",
      "isDone": false
    },
    {
      "id": "a665",
      "eng": "22",
      "kor": "22",
      "day": "1",
      "isDone": false
    },
    {
      "id": "b76e",
      "eng": "3",
      "kor": "3",
      "day": "1",
      "isDone": false
    },
    {
      "id": "7fcc",
      "eng": "33",
      "kor": "43",
      "day": "1",
      "isDone": false
    },
    {
      "id": "c13d",
      "eng": "ss",
      "kor": "ss",
      "day": "1",
      "isDone": false
    },
    {
      "id": "f715",
      "eng": "234",
      "kor": "42343",
      "day": "1",
      "isDone": false
    },
    {
      "id": "1ae2",
      "eng": "2",
      "kor": "2",
      "day": "1",
      "isDone": false
    },
    {
      "id": "adb5",
      "eng": "33",
      "kor": "3333",
      "day": "1",
      "isDone": false
    },
    {
      "id": "5e38",
      "eng": "ss",
      "kor": "sssss",
      "day": "1",
      "isDone": false
    },
    {
      "id": "4698",
      "eng": "454545",
      "kor": "45454",
      "day": "2",
      "isDone": false
    },
    {
      "id": "59f5",
      "eng": "sss",
      "kor": "sssss",
      "day": "1",
      "isDone": false
    },
    {
      "id": "8ac3",
      "eng": "vv",
      "kor": "vvv",
      "day": "1",
      "isDone": false
    },
    {
      "id": "9306",
      "eng": "sss",
      "kor": "ss",
      "day": "3",
      "isDone": false
    },
    {
      "id": "a1e1",
      "eng": "2e2e",
      "kor": "e22",
      "day": "4",
      "isDone": false
    },
    {
      "id": "428e",
      "eng": "qwe",
      "kor": "qweqw",
      "day": "1",
      "isDone": false
    },
    {
      "id": "a4ed",
      "eng": "22",
      "kor": "333",
      "day": "1",
      "isDone": false
    },
    {
      "id": "8624",
      "eng": "123",
      "kor": "123",
      "day": "12",
      "isDone": false
    },
    {
      "id": "025c",
      "eng": "12323",
      "kor": "2323",
      "day": "12",
      "isDone": false
    },
    {
      "id": "f516",
      "eng": "12323",
      "kor": "2323",
      "day": "12",
      "isDone": false
    },
    {
      "id": "be7a",
      "eng": "343",
      "kor": "3434",
      "day": "12",
      "isDone": false
    },
    {
      "id": "c9d5",
      "eng": "apple",
      "kor": "1",
      "day": "1",
      "isDone": false
    },
    {
      "id": "6c19",
      "eng": "77",
      "kor": "77",
      "day": "12",
      "isDone": false
    },
    {
      "id": "4054",
      "eng": "테스트",
      "kor": "123",
      "day": "13",
      "isDone": false
    }
  ]
}